{
  "items": [
    {
      "title": "Home",
      "arg": "18",
      "space_hash": 168,
      "screens_hashes": [
        69732352
      ]
    },
    {
      "title": "Space 2",
      "arg": "19",
      "space_hash": 572,
      "screens_hashes": [
        69732352
      ]
    },
    {
      "title": "Space 3",
      "arg": "20",
      "space_hash": 306,
      "screens_hashes": [
        69732352
      ]
    },
    {
      "title": "Space 4",
      "arg": "21",
      "space_hash": 465,
      "screens_hashes": [
        69732352
      ]
    },
    {
      "title": "Space 4",
      "arg": "21",
      "space_hash": 270,
      "screens_hashes": [
        69732352
      ]
    },
    {
      "title": "Space 6",
      "arg": "22",
      "space_hash": 611,
      "screens_hashes": [
        69732352
      ]
    }
  ]
}
